cytools/__init__.c
cytools/__init__.html
cytools/__init__.py
cytools/__init__.pyx
cytools/_finalizer.c
cytools/_finalizer.html
cytools/_finalizer.pyx
cytools/_functions.c
cytools/_functions.html
cytools/_functions.pyx
cytools/math.c
cytools/math.cpython-38-x86_64-linux-gnu.so
cytools/math.html
cytools/math.pxd
cytools/math.pyx
cytools/mvtools.c
cytools/mvtools.html
cytools/mvtools.pyx
develia_cytools-0.1.0.dist-info/METADATA
develia_cytools-0.1.0.dist-info/WHEEL
develia_cytools-0.1.0.dist-info/RECORD
