Metadata-Version: 2.4
Name: develia-cytools
Version: 0.1.0
Summary: Cython utility library.
Author: Antonio Gil Espinosa
Author-email: antonio.gil.espinosa@gmail.com
Requires-Python: >=3.9,<4.0
Classifier: Programming Language :: Python :: 3
Classifier: Programming Language :: Python :: 3.9
Classifier: Programming Language :: Python :: 3.10
Classifier: Programming Language :: Python :: 3.11
Classifier: Programming Language :: Python :: 3.12
Classifier: Programming Language :: Python :: 3.13
Classifier: Programming Language :: Python :: 3.14
Requires-Dist: cython (==3.2.1)
Requires-Dist: poetry-core (>=2.2.1,<3.0.0)
Requires-Dist: setuptools (>=80.9.0,<81.0.0)
